{"bundler_unplugin-uni-app-tailwind.md":"6572dec1","composition_uni-app-use.md":"bab87395","editor_vscode-uni-app-schemas.md":"78045daf","editor_vscode-uni-app-snippets.md":"b15e694a","editor_vscode-uni-cloud-snippets.md":"2409fbb1","editor_vscode-uni-helper.md":"ff27b560","editor_vscode-uni-ui-snippets.md":"6e48f75c","index.md":"e114c8a8","overview.md":"efce2ea7","request_uni-request.md":"67e994ea","typescript_uni-app-types.md":"b221c7c3","typescript_uni-cloud-types.md":"491ae65a","typescript_uni-ui-types.md":"96405947"}
